kmock/.gitignore
kmock/__init__.py
kmock/_version.py
kmock/py.typed
kmock/_internal/__init__.py
kmock/_internal/aiobus.py
kmock/_internal/apps.py
kmock/_internal/boxes.py
kmock/_internal/dns.py
kmock/_internal/dsl.py
kmock/_internal/enums.py
kmock/_internal/filtering.py
kmock/_internal/k8s.py
kmock/_internal/k8s_dicts.py
kmock/_internal/k8s_views.py
kmock/_internal/parsing.py
kmock/_internal/pytest.py
kmock/_internal/rendering.py
kmock/_internal/resources.py
kmock-0.3.dist-info/licenses/LICENSE
kmock-0.3.dist-info/METADATA
kmock-0.3.dist-info/WHEEL
kmock-0.3.dist-info/entry_points.txt
kmock-0.3.dist-info/top_level.txt
kmock-0.3.dist-info/RECORD
