Metadata-Version: 2.4
Name: kmock
Version: 0.3
Summary: HTTP/API/Kubernetes Mock Server
Author-email: Sergey Vasilyev <nolar@nolar.info>
Maintainer-email: Sergey Vasilyev <nolar@nolar.info>
License-Expression: MIT
Project-URL: homepage, https://github.com/nolar/kmock
Project-URL: repository, https://github.com/nolar/kmock
Project-URL: documentation, https://kmock.readthedocs.io
Keywords: kubernetes,k8s,api,server,mock,testing,python,pytest,unittest
Classifier: Intended Audience :: Developers
Classifier: Operating System :: OS Independent
Classifier: Framework :: AsyncIO
Classifier: Framework :: Pytest
Classifier: Framework :: aiohttp
Classifier: Programming Language :: Python
Classifier: Programming Language :: Python :: 3
Classifier: Topic :: Internet :: WWW/HTTP
Classifier: Topic :: Internet :: WWW/HTTP :: HTTP Servers
Classifier: Topic :: Software Development :: Libraries
Classifier: Topic :: Software Development :: Libraries :: Python Modules
Classifier: Topic :: Software Development :: Testing
Classifier: Topic :: Software Development :: Testing :: Mocking
Classifier: Topic :: Software Development :: Testing :: Unit
Classifier: Programming Language :: Python :: 3.10
Classifier: Programming Language :: Python :: 3.11
Classifier: Programming Language :: Python :: 3.12
Classifier: Programming Language :: Python :: 3.13
Classifier: Programming Language :: Python :: 3.14
Classifier: Programming Language :: Python :: 3 :: Only
Classifier: Programming Language :: Python :: Implementation :: CPython
Classifier: Programming Language :: Python :: Implementation :: PyPy
Classifier: Typing :: Typed
Requires-Python: >=3.10
License-File: LICENSE
Requires-Dist: attrs
Requires-Dist: yarl
Requires-Dist: aiohttp>=3.9.0b0
Requires-Dist: typing_extensions>=4.4.0
Dynamic: license-file
